radar_server/__init__.py
radar_server/exceptions.py
radar_server/fields/__init__.py
radar_server/fields/array.py
radar_server/fields/field.py
radar_server/fields/mapping.py
radar_server/query.py
radar_server/record.py
radar_server/resolver.py
radar_server/union.py
radar_server/utils.py
radar_server-0.1.5.dist-info/entry_points.txt
radar_server-0.1.5.dist-info/LICENSE
radar_server-0.1.5.dist-info/WHEEL
radar_server-0.1.5.dist-info/METADATA
radar_server-0.1.5.dist-info/RECORD
